mlflowapi/__init__.py
mlflowapi-0.2.dist-info/LICENSE.txt
mlflowapi-0.2.dist-info/METADATA
mlflowapi-0.2.dist-info/WHEEL
mlflowapi-0.2.dist-info/top_level.txt
mlflowapi-0.2.dist-info/RECORD
